wa_crypt_tools/__init__.py
wa_crypt_tools/wacreatekey.py
wa_crypt_tools/wadecrypt.py
wa_crypt_tools/waencrypt.py
wa_crypt_tools/waguess.py
wa_crypt_tools/wainfo.py
wa_crypt_tools/lib/constants.py
wa_crypt_tools/lib/logformat.py
wa_crypt_tools/lib/props.py
wa_crypt_tools/lib/utils.py
wa_crypt_tools/lib/db/db.py
wa_crypt_tools/lib/db/db12.py
wa_crypt_tools/lib/db/db14.py
wa_crypt_tools/lib/db/db15.py
wa_crypt_tools/lib/db/dbfactory.py
wa_crypt_tools/lib/key/key.py
wa_crypt_tools/lib/key/key14.py
wa_crypt_tools/lib/key/key15.py
wa_crypt_tools/lib/key/keyfactory.py
wa_crypt_tools/proto/C14_cipher_pb2.py
wa_crypt_tools/proto/C15_IV_pb2.py
wa_crypt_tools/proto/__init__.py
wa_crypt_tools/proto/backup_expiry_pb2.py
wa_crypt_tools/proto/backup_prefix_pb2.py
wa_crypt_tools/proto/key_type_pb2.py
wa_crypt_tools-0.1.0.dist-info/LICENSE
wa_crypt_tools-0.1.0.dist-info/METADATA
wa_crypt_tools-0.1.0.dist-info/WHEEL
wa_crypt_tools-0.1.0.dist-info/entry_points.txt
wa_crypt_tools-0.1.0.dist-info/top_level.txt
wa_crypt_tools-0.1.0.dist-info/RECORD
