Metadata-Version: 2.1
Name: wa-crypt-tools
Version: 0.1.0
Summary: Manages WhatsApp .crypt12, .crypt14 and .crypt15 files, given the key.
Author-email: Davide Palma <pypi@davidepalma.it>
Keywords: whatsapp,crypt12,crypt14,crypt15
Classifier: Environment :: Console
Classifier: Intended Audience :: End Users/Desktop
Classifier: License :: OSI Approved :: GNU General Public License v3 or later (GPLv3+)
Classifier: Operating System :: OS Independent
Classifier: Topic :: Security :: Cryptography
Classifier: Topic :: Software Development :: Libraries :: Python Modules
Classifier: Topic :: Utilities
Classifier: Programming Language :: Python :: 3
Classifier: Programming Language :: Python :: 3.8
Classifier: Programming Language :: Python :: 3.9
Classifier: Programming Language :: Python :: 3.10
Classifier: Programming Language :: Python :: 3.11
Classifier: Programming Language :: Python :: 3.12
Requires-Python: >=3.8
License-File: LICENSE
Requires-Dist: javaobj-py3>=0.4.4
Requires-Dist: pycryptodomex>=3.20.0
Requires-Dist: protobuf<5.28.0,>=5.27.3
Provides-Extra: proto
Requires-Dist: protoletariat; extra == "proto"
